odoo/addons/account_statement_import_coda/README.rst
odoo/addons/account_statement_import_coda/__init__.py
odoo/addons/account_statement_import_coda/__manifest__.py
odoo/addons/account_statement_import_coda/i18n/account_statement_import_coda.pot
odoo/addons/account_statement_import_coda/i18n/ca_ES.po
odoo/addons/account_statement_import_coda/i18n/de.po
odoo/addons/account_statement_import_coda/i18n/fi.po
odoo/addons/account_statement_import_coda/i18n/fr.po
odoo/addons/account_statement_import_coda/i18n/nl_NL.po
odoo/addons/account_statement_import_coda/models/__init__.py
odoo/addons/account_statement_import_coda/models/account_journal.py
odoo/addons/account_statement_import_coda/readme/CONTRIBUTORS.rst
odoo/addons/account_statement_import_coda/readme/DESCRIPTION.rst
odoo/addons/account_statement_import_coda/readme/INSTALL.rst
odoo/addons/account_statement_import_coda/static/description/icon.png
odoo/addons/account_statement_import_coda/static/description/index.html
odoo/addons/account_statement_import_coda/test_coda_file/Ontvangen_CODA.2012-01-11-18.59.15.txt
odoo/addons/account_statement_import_coda/tests/__init__.py
odoo/addons/account_statement_import_coda/tests/test_import_statement.py
odoo/addons/account_statement_import_coda/wizard/__init__.py
odoo/addons/account_statement_import_coda/wizard/account_statement_import_coda.py
odoo/addons/account_statement_import_coda/wizard/account_statement_import_coda_view.xml
odoo14_addon_account_statement_import_coda-14.0.1.0.4.dist-info/METADATA
odoo14_addon_account_statement_import_coda-14.0.1.0.4.dist-info/WHEEL
odoo14_addon_account_statement_import_coda-14.0.1.0.4.dist-info/top_level.txt
odoo14_addon_account_statement_import_coda-14.0.1.0.4.dist-info/RECORD
